logcatparser
