Metadata-Version: 2.1
Name: pylogcatparser
Version: 0.2.4
Summary: LogCatParser: A simple Android logcat parser
Home-page: https://github.com/RRua/logcatparser
Author: Rui Rua
Author-email: rui.rrua@gmail.com
License: MIT
Project-URL: Bug Tracker, https://github.com/RRua/logcatparser/issues
Platform: UNKNOWN
Classifier: License :: OSI Approved :: MIT License
Classifier: Intended Audience :: Science/Research
Classifier: Operating System :: POSIX
Classifier: Programming Language :: Python :: 3.8
Requires-Python: >=3.6
